<?xml version="1.0" encoding="utf-8"?>
<GameData>
	<Types>
		<Row Type="CIVILIZATION_BEOR" Kind="KIND_CIVILIZATION"/>
		<Row Type="LEADER_MINOR_CIV_BEOR" Kind="KIND_LEADER"/>
		<Row Type="MINOR_CIV_BEOR_TRAIT" Kind="KIND_TRAIT"/>

		<Row Type="CIVILIZATION_HALADIN" Kind="KIND_CIVILIZATION"/> <!-- Haleth-->
		<Row Type="LEADER_MINOR_CIV_HALADIN" Kind="KIND_LEADER"/>
		<Row Type="MINOR_CIV_HALADIN_TRAIT" Kind="KIND_TRAIT"/>

		<Row Type="CIVILIZATION_MARACH" Kind="KIND_CIVILIZATION"/>
		<Row Type="LEADER_MINOR_CIV_MARACH" Kind="KIND_LEADER"/>
		<Row Type="MINOR_CIV_MARACH_TRAIT" Kind="KIND_TRAIT"/>

		<Row Type="CIVILIZATION_BOR" Kind="KIND_CIVILIZATION"/>
		<Row Type="LEADER_MINOR_CIV_BOR" Kind="KIND_LEADER"/>
		<Row Type="MINOR_CIV_BOR_TRAIT" Kind="KIND_TRAIT"/>

		<Row Type="CIVILIZATION_ULFANG" Kind="KIND_CIVILIZATION"/>
		<Row Type="LEADER_MINOR_CIV_ULFANG" Kind="KIND_LEADER"/>
		<Row Type="MINOR_CIV_ULFANG_TRAIT" Kind="KIND_TRAIT"/>
		<Row Type="ABILITY_ULFANG_GRANT" Kind="KIND_ABILITY"/>

		<Row Type="CIVILIZATION_BELEGOST" Kind="KIND_CIVILIZATION"/>
		<Row Type="LEADER_MINOR_CIV_BELEGOST" Kind="KIND_LEADER"/>
		<Row Type="MINOR_CIV_BELEGOST_TRAIT" Kind="KIND_TRAIT"/>


		<Row Type="CIVILIZATION_NOGROD" Kind="KIND_CIVILIZATION"/>
		<Row Type="LEADER_MINOR_CIV_NOGROD" Kind="KIND_LEADER"/>
		<Row Type="MINOR_CIV_NOGROD_TRAIT" Kind="KIND_TRAIT"/>

		<Row Type="CIVILIZATION_FALAS" Kind="KIND_CIVILIZATION"/>
		<Row Type="LEADER_MINOR_CIV_FALAS" Kind="KIND_LEADER"/>
		<Row Type="MINOR_CIV_FALAS_TRAIT" Kind="KIND_TRAIT"/>

		<Row Type="CIVILIZATION_EOL" Kind="KIND_CIVILIZATION"/>
		<Row Type="LEADER_MINOR_CIV_EOL" Kind="KIND_LEADER"/>
		<Row Type="MINOR_CIV_EOL_TRAIT" Kind="KIND_TRAIT"/>

		<Row Type="CIVILIZATION_PETTYDWARVES" Kind="KIND_CIVILIZATION"/>
		<Row Type="LEADER_MINOR_CIV_PETTYDWARVES" Kind="KIND_LEADER"/>
		<Row Type="MINOR_CIV_PETTYDWARVES_TRAIT" Kind="KIND_TRAIT"/>

		<Row Type="CIVILIZATION_BALAR" Kind="KIND_CIVILIZATION"/>
		<Row Type="LEADER_MINOR_CIV_BALAR" Kind="KIND_LEADER"/>
		<Row Type="MINOR_CIV_BALAR_TRAIT" Kind="KIND_TRAIT"/>

		<Row Type="CIVILIZATION_SIRION" Kind="KIND_CIVILIZATION"/>
		<Row Type="LEADER_MINOR_CIV_SIRION" Kind="KIND_LEADER"/>
		<Row Type="MINOR_CIV_SIRION_TRAIT" Kind="KIND_TRAIT"/>

		<Row Type="CIVILIZATION_BRODDA" Kind="KIND_CIVILIZATION"/>
		<Row Type="LEADER_MINOR_CIV_BRODDA" Kind="KIND_LEADER"/>
		<Row Type="MINOR_CIV_BRODDA_TRAIT" Kind="KIND_TRAIT"/>

		<Row Type="CIVILIZATION_LORGAN" Kind="KIND_CIVILIZATION"/>
		<Row Type="LEADER_MINOR_CIV_LORGAN" Kind="KIND_LEADER"/>
		<Row Type="MINOR_CIV_LORGAN_TRAIT" Kind="KIND_TRAIT"/>

		<Row Type="CIVILIZATION_HADOR" Kind="KIND_CIVILIZATION"/>
		<Row Type="LEADER_MINOR_CIV_HADOR" Kind="KIND_LEADER"/>
		<Row Type="MINOR_CIV_HADOR_TRAIT" Kind="KIND_TRAIT"/>

		<Row Type="CIVILIZATION_BEOR_LADROS" Kind="KIND_CIVILIZATION"/>
		<Row Type="LEADER_MINOR_CIV_BEOR_LADROS" Kind="KIND_LEADER"/>
		<Row Type="MINOR_CIV_BEOR_LADROS_TRAIT" Kind="KIND_TRAIT"/>

		<Row Type="CIVILIZATION_DOR_CUARTHOL" Kind="KIND_CIVILIZATION"/>
		<Row Type="LEADER_MINOR_CIV_DOR_CUARTHOL" Kind="KIND_LEADER"/>
		<Row Type="MINOR_CIV_DOR_CUARTHOL_TRAIT" Kind="KIND_TRAIT"/>
	</Types>

	<Leaders>
		<Row LeaderType="LEADER_MINOR_CIV_BEOR" Name="LOC_CITY_NAME_BEOR" InheritFrom="LEADER_MINOR_CIV_CULTURAL"/>
		<Row LeaderType="LEADER_MINOR_CIV_HALADIN" Name="LOC_CITY_NAME_HALADIN" InheritFrom="LEADER_MINOR_CIV_RELIGIOUS"/>
		<Row LeaderType="LEADER_MINOR_CIV_MARACH" Name="LOC_CITY_NAME_MARACH" InheritFrom="LEADER_MINOR_CIV_MILITARISTIC"/>
		<Row LeaderType="LEADER_MINOR_CIV_BOR" Name="LOC_CITY_NAME_BOR" InheritFrom="LEADER_MINOR_CIV_MILITARISTIC"/>
		<Row LeaderType="LEADER_MINOR_CIV_ULFANG" Name="LOC_CITY_NAME_ULFANG" InheritFrom="LEADER_MINOR_CIV_MILITARISTIC"/>
		<Row LeaderType="LEADER_MINOR_CIV_BELEGOST" Name="LOC_CITY_NAME_BELEGOST" InheritFrom="LEADER_MINOR_CIV_TRADE"/>
		<Row LeaderType="LEADER_MINOR_CIV_NOGROD" Name="LOC_CITY_NAME_NOGROD" InheritFrom="LEADER_MINOR_CIV_INDUSTRIAL"/>
		<Row LeaderType="LEADER_MINOR_CIV_FALAS" Name="LOC_CITY_NAME_FALAS" InheritFrom="LEADER_MINOR_CIV_TRADE"/>
		<Row LeaderType="LEADER_MINOR_CIV_EOL" Name="LOC_CITY_NAME_EOL" InheritFrom="LEADER_MINOR_CIV_INDUSTRIAL"/>
		<Row LeaderType="LEADER_MINOR_CIV_PETTYDWARVES" Name="LOC_CITY_NAME_BARENNIBINNOEG" InheritFrom="LEADER_MINOR_CIV_CULTURAL"/>
		<Row LeaderType="LEADER_MINOR_CIV_BALAR" Name="LOC_CITY_NAME_BALAR" InheritFrom="LEADER_MINOR_CIV_RELIGIOUS"/>
		<Row LeaderType="LEADER_MINOR_CIV_SIRION" Name="LOC_CITY_NAME_HAVENS_OF_SIRION" InheritFrom="LEADER_MINOR_CIV_CULTURAL"/>
		<Row LeaderType="LEADER_MINOR_CIV_BRODDA" Name="LOC_CITY_NAME_BRODDA" InheritFrom="LEADER_MINOR_CIV_RELIGIOUS"/>
		<Row LeaderType="LEADER_MINOR_CIV_LORGAN" Name="LOC_CITY_NAME_LORGAN" InheritFrom="LEADER_MINOR_CIV_INDUSTRIAL"/>
		<Row LeaderType="LEADER_MINOR_CIV_HADOR" Name="LOC_CITY_NAME_HADOR" InheritFrom="LEADER_MINOR_CIV_MILITARISTIC"/>
		<Row LeaderType="LEADER_MINOR_CIV_BEOR_LADROS" Name="LOC_CITY_NAME_BEOR_LADROS" InheritFrom="LEADER_MINOR_CIV_CULTURAL"/>
		<Row LeaderType="LEADER_MINOR_CIV_DOR_CUARTHOL" Name="LOC_CITY_NAME_DOR_CUARTHOL" InheritFrom="LEADER_MINOR_CIV_MILITARISTIC"/>

	</Leaders>

	<LeaderTraits>
		<Row LeaderType="LEADER_MINOR_CIV_BEOR" TraitType="MINOR_CIV_BEOR_TRAIT"/>
		<Row LeaderType="LEADER_MINOR_CIV_HALADIN" TraitType="MINOR_CIV_HALADIN_TRAIT"/>
		<Row LeaderType="LEADER_MINOR_CIV_MARACH" TraitType="MINOR_CIV_MARACH_TRAIT"/>
		<Row LeaderType="LEADER_MINOR_CIV_BOR" TraitType="MINOR_CIV_BOR_TRAIT"/>
		<Row LeaderType="LEADER_MINOR_CIV_ULFANG" TraitType="MINOR_CIV_ULFANG_TRAIT"/>
		<Row LeaderType="LEADER_MINOR_CIV_BELEGOST" TraitType="MINOR_CIV_BELEGOST_TRAIT"/>
		<Row LeaderType="LEADER_MINOR_CIV_NOGROD" TraitType="MINOR_CIV_NOGROD_TRAIT"/>
		<Row LeaderType="LEADER_MINOR_CIV_FALAS" TraitType="MINOR_CIV_FALAS_TRAIT"/>
		<Row LeaderType="LEADER_MINOR_CIV_EOL" TraitType="MINOR_CIV_EOL_TRAIT"/>
		<Row LeaderType="LEADER_MINOR_CIV_PETTYDWARVES" TraitType="MINOR_CIV_PETTYDWARVES_TRAIT"/>
		<Row LeaderType="LEADER_MINOR_CIV_BALAR" TraitType="MINOR_CIV_BALAR_TRAIT"/>
		<Row LeaderType="LEADER_MINOR_CIV_SIRION" TraitType="MINOR_CIV_SIRION_TRAIT"/>
		<Row LeaderType="LEADER_MINOR_CIV_BRODDA" TraitType="MINOR_CIV_BRODDA_TRAIT"/>
		<Row LeaderType="LEADER_MINOR_CIV_LORGAN" TraitType="MINOR_CIV_LORGAN_TRAIT"/>
		<Row LeaderType="LEADER_MINOR_CIV_HADOR" TraitType="MINOR_CIV_HADOR_TRAIT"/>
		<Row LeaderType="LEADER_MINOR_CIV_BEOR_LADROS" TraitType="MINOR_CIV_BEOR_LADROS_TRAIT"/>
		<Row LeaderType="LEADER_MINOR_CIV_DOR_CUARTHOL" TraitType="MINOR_CIV_DOR_CUARTHOL_TRAIT"/>

	</LeaderTraits>

	<CivilizationTraits>
		<Row CivilizationType="CIVILIZATION_BEOR" TraitType="TRAIT_CIVILIZATION_UNIT_EDAIN_PHALANXES"/>
		<Row CivilizationType="CIVILIZATION_HALADIN" TraitType="TRAIT_CIVILIZATION_UNIT_EDAIN_PHALANXES"/>
		<Row CivilizationType="CIVILIZATION_MARACH" TraitType="TRAIT_CIVILIZATION_UNIT_EDAIN_PHALANXES"/>
		<Row CivilizationType="CIVILIZATION_BOR" TraitType="TRAIT_CIVILIZATION_UNIT_EDAIN_PHALANXES"/>
		<Row CivilizationType="CIVILIZATION_BELEGOST" TraitType="TRAIT_CIVILIZATION_UNIT_DWARVEN_GUARDIAN"/>
		<Row CivilizationType="CIVILIZATION_BELEGOST" TraitType="TRAIT_CIVILIZATION_UNIT_DWARVEN_PHALANXES"/>
		<Row CivilizationType="CIVILIZATION_BELEGOST" TraitType="TRAIT_CIVILIZATION_UNIT_GOAT_RIDERS"/>
		<Row CivilizationType="CIVILIZATION_BELEGOST" TraitType="TRAIT_CIVILIZATION_UNIT_BOAR_RIDERS"/>
		<Row CivilizationType="CIVILIZATION_BELEGOST" TraitType="TRAIT_CIVILIZATION_BUILDING_DWARVEN_EXCAVATION"/>
		<Row CivilizationType="CIVILIZATION_BELEGOST" TraitType="TRAIT_CIVILIZATION_UNIT_DWARF_AXE_THROWER"/>
		<Row CivilizationType="CIVILIZATION_BELEGOST" TraitType="TRAIT_CIVILIZATION_UNIT_DWARF_BATTLEWAGON"/>
		<Row CivilizationType="CIVILIZATION_BELEGOST" TraitType="TRAIT_CIVILIZATION_BUILDING_DWARVEN_DOORS"/>
		<Row CivilizationType="CIVILIZATION_BELEGOST" TraitType="TRAIT_CIVILIZATION_BUILDING_DWARVEN_HALLS"/>
		<Row CivilizationType="CIVILIZATION_NOGROD" TraitType="TRAIT_CIVILIZATION_UNIT_DWARVEN_GUARDIAN"/>
		<Row CivilizationType="CIVILIZATION_NOGROD" TraitType="TRAIT_CIVILIZATION_UNIT_DWARVEN_PHALANXES"/>
		<Row CivilizationType="CIVILIZATION_NOGROD" TraitType="TRAIT_CIVILIZATION_UNIT_GOAT_RIDERS"/>
		<Row CivilizationType="CIVILIZATION_NOGROD" TraitType="TRAIT_CIVILIZATION_UNIT_BOAR_RIDERS"/>
		<Row CivilizationType="CIVILIZATION_NOGROD" TraitType="TRAIT_CIVILIZATION_BUILDING_DWARVEN_EXCAVATION"/>
		<Row CivilizationType="CIVILIZATION_NOGROD" TraitType="TRAIT_CIVILIZATION_UNIT_DWARF_AXE_THROWER"/>
		<Row CivilizationType="CIVILIZATION_NOGROD" TraitType="TRAIT_CIVILIZATION_UNIT_DWARF_BATTLEWAGON"/>
		<Row CivilizationType="CIVILIZATION_NOGROD" TraitType="TRAIT_CIVILIZATION_BUILDING_DWARVEN_DOORS"/>
		<Row CivilizationType="CIVILIZATION_NOGROD" TraitType="TRAIT_CIVILIZATION_BUILDING_DWARVEN_HALLS"/>
		<Row CivilizationType="CIVILIZATION_FALAS" TraitType="TRAIT_CIVILIZATION_UNIT_TELERI_WARRIOR"/>
		<Row CivilizationType="CIVILIZATION_FALAS" TraitType="TRAIT_CIVILIZATION_UNIT_MITHLOND_SENTRY"/>
		<Row CivilizationType="CIVILIZATION_FALAS" TraitType="TRAIT_CIVILIZATION_UNIT_HIGH_ELF_ARCHER"/>
		<Row CivilizationType="CIVILIZATION_FALAS" TraitType="TRAIT_CIVILIZATION_UNIT_ELDAR_MOUNTED_ARCHER"/>
		<Row CivilizationType="CIVILIZATION_FALAS" TraitType="TRAIT_CIVILIZATION_UNIT_ELDAR_CAVALRY"/>
		<Row CivilizationType="CIVILIZATION_FALAS" TraitType="TRAIT_CIVILIZATION_UNIT_TELERI_SWANSHIP"/>
		<Row CivilizationType="CIVILIZATION_FALAS" TraitType="TRAIT_CIVILIZATION_IMPROVEMENT_ELVEN_TOWER"/>
		<Row CivilizationType="CIVILIZATION_FALAS" TraitType="TRAIT_CIVILIZATION_IMPROVEMENT_ELVEN_HOUSE"/>
		<Row CivilizationType="CIVILIZATION_EOL" TraitType="TRAIT_CIVILIZATION_UNIT_TELERI_WARRIOR"/>
		<Row CivilizationType="CIVILIZATION_EOL" TraitType="TRAIT_CIVILIZATION_UNIT_MITHLOND_SENTRY"/>
		<Row CivilizationType="CIVILIZATION_EOL" TraitType="TRAIT_CIVILIZATION_UNIT_HIGH_ELF_ARCHER"/>
		<Row CivilizationType="CIVILIZATION_EOL" TraitType="TRAIT_CIVILIZATION_UNIT_ELDAR_MOUNTED_ARCHER"/>
		<Row CivilizationType="CIVILIZATION_EOL" TraitType="TRAIT_CIVILIZATION_UNIT_ELDAR_CAVALRY"/>
		<Row CivilizationType="CIVILIZATION_EOL" TraitType="TRAIT_CIVILIZATION_UNIT_TELERI_SWANSHIP"/>
		<Row CivilizationType="CIVILIZATION_PETTYDWARVES" TraitType="TRAIT_CIVILIZATION_UNIT_DWARVEN_GUARDIAN"/>
		<Row CivilizationType="CIVILIZATION_PETTYDWARVES" TraitType="TRAIT_CIVILIZATION_UNIT_DWARVEN_PHALANXES"/>
		<Row CivilizationType="CIVILIZATION_PETTYDWARVES" TraitType="TRAIT_CIVILIZATION_UNIT_GOAT_RIDERS"/>
		<Row CivilizationType="CIVILIZATION_PETTYDWARVES" TraitType="TRAIT_CIVILIZATION_UNIT_BOAR_RIDERS"/>
		<Row CivilizationType="CIVILIZATION_PETTYDWARVES" TraitType="TRAIT_CIVILIZATION_BUILDING_DWARVEN_EXCAVATION"/>
		<Row CivilizationType="CIVILIZATION_PETTYDWARVES" TraitType="TRAIT_CIVILIZATION_UNIT_DWARF_AXE_THROWER"/>
		<Row CivilizationType="CIVILIZATION_PETTYDWARVES" TraitType="TRAIT_CIVILIZATION_UNIT_DWARF_BATTLEWAGON"/>
		<Row CivilizationType="CIVILIZATION_PETTYDWARVES" TraitType="TRAIT_CIVILIZATION_BUILDING_DWARVEN_DOORS"/>
		<Row CivilizationType="CIVILIZATION_PETTYDWARVES" TraitType="TRAIT_CIVILIZATION_BUILDING_DWARVEN_HALLS"/>
		<Row CivilizationType="CIVILIZATION_BALAR" TraitType="TRAIT_CIVILIZATION_UNIT_TELERI_WARRIOR"/>
		<Row CivilizationType="CIVILIZATION_BALAR" TraitType="TRAIT_CIVILIZATION_UNIT_MITHLOND_SENTRY"/>
		<Row CivilizationType="CIVILIZATION_BALAR" TraitType="TRAIT_CIVILIZATION_UNIT_HIGH_ELF_ARCHER"/>
		<Row CivilizationType="CIVILIZATION_BALAR" TraitType="TRAIT_CIVILIZATION_UNIT_ELDAR_MOUNTED_ARCHER"/>
		<Row CivilizationType="CIVILIZATION_BALAR" TraitType="TRAIT_CIVILIZATION_UNIT_ELDAR_CAVALRY"/>
		<Row CivilizationType="CIVILIZATION_BALAR" TraitType="TRAIT_CIVILIZATION_UNIT_TELERI_SWANSHIP"/>
		<Row CivilizationType="CIVILIZATION_BALAR" TraitType="TRAIT_CIVILIZATION_IMPROVEMENT_ELVEN_TOWER"/>
		<Row CivilizationType="CIVILIZATION_BALAR" TraitType="TRAIT_CIVILIZATION_IMPROVEMENT_ELVEN_HOUSE"/>
		<Row CivilizationType="CIVILIZATION_SIRION" TraitType="TRAIT_CIVILIZATION_UNIT_TELERI_WARRIOR"/>
		<Row CivilizationType="CIVILIZATION_SIRION" TraitType="TRAIT_CIVILIZATION_UNIT_MITHLOND_SENTRY"/>
		<Row CivilizationType="CIVILIZATION_SIRION" TraitType="TRAIT_CIVILIZATION_UNIT_HIGH_ELF_ARCHER"/>
		<Row CivilizationType="CIVILIZATION_SIRION" TraitType="TRAIT_CIVILIZATION_UNIT_ELDAR_MOUNTED_ARCHER"/>
		<Row CivilizationType="CIVILIZATION_SIRION" TraitType="TRAIT_CIVILIZATION_UNIT_ELDAR_CAVALRY"/>
		<Row CivilizationType="CIVILIZATION_SIRION" TraitType="TRAIT_CIVILIZATION_UNIT_TELERI_SWANSHIP"/>
		<Row CivilizationType="CIVILIZATION_SIRION" TraitType="TRAIT_CIVILIZATION_IMPROVEMENT_ELVEN_TOWER"/>
		<Row CivilizationType="CIVILIZATION_SIRION" TraitType="TRAIT_CIVILIZATION_IMPROVEMENT_ELVEN_HOUSE"/>
		<Row CivilizationType="CIVILIZATION_HADOR" TraitType="TRAIT_CIVILIZATION_UNIT_EDAIN_PHALANXES"/>
		<Row CivilizationType="CIVILIZATION_BEOR_LADROS" TraitType="TRAIT_CIVILIZATION_UNIT_EDAIN_PHALANXES"/>
		<Row CivilizationType="CIVILIZATION_DOR_CUARTHOL" TraitType="TRAIT_CIVILIZATION_UNIT_EDAIN_PHALANXES"/>
		<Row CivilizationType="CIVILIZATION_DOR_CUARTHOL" TraitType="TRAIT_CIVILIZATION_UNIT_TELERI_WARRIOR"/>
		<Row CivilizationType="CIVILIZATION_DOR_CUARTHOL" TraitType="TRAIT_CIVILIZATION_UNIT_HIGH_ELF_ARCHER"/>
		<Row CivilizationType="CIVILIZATION_DOR_CUARTHOL" TraitType="TRAIT_CIVILIZATION_UNIT_ELDAR_MOUNTED_ARCHER"/>
		<Row CivilizationType="CIVILIZATION_DOR_CUARTHOL" TraitType="TRAIT_CIVILIZATION_UNIT_ELDAR_CAVALRY"/>

	</CivilizationTraits>

	<Traits>
		<Row TraitType="MINOR_CIV_BEOR_TRAIT" Name="LOC_MINOR_CIV_BEOR_TRAIT_NAME" Description="LOC_MINOR_CIV_BEOR_TRAIT_DESCRIPTION"/>
		<Row TraitType="MINOR_CIV_HALADIN_TRAIT" Name="LOC_MINOR_CIV_HALADIN_TRAIT_NAME" Description="LOC_MINOR_CIV_HALADIN_TRAIT_DESCRIPTION"/>
		<Row TraitType="MINOR_CIV_MARACH_TRAIT" Name="LOC_MINOR_CIV_MARACH_TRAIT_NAME" Description="LOC_MINOR_CIV_MARACH_TRAIT_DESCRIPTION"/>
		<Row TraitType="MINOR_CIV_BOR_TRAIT" Name="LOC_MINOR_CIV_BOR_TRAIT_NAME" Description="LOC_MINOR_CIV_BOR_TRAIT_DESCRIPTION"/>
		<Row TraitType="MINOR_CIV_ULFANG_TRAIT" Name="LOC_MINOR_CIV_ULFANG_TRAIT_NAME" Description="LOC_MINOR_CIV_ULFANG_TRAIT_DESCRIPTION"/>
		<Row TraitType="MINOR_CIV_BELEGOST_TRAIT" Name="LOC_MINOR_CIV_BELEGOST_TRAIT_NAME" Description="LOC_MINOR_CIV_BELEGOST_TRAIT_DESCRIPTION"/>
		<Row TraitType="MINOR_CIV_NOGROD_TRAIT" Name="LOC_MINOR_CIV_NOGROD_TRAIT_NAME" Description="LOC_MINOR_CIV_NOGROD_TRAIT_DESCRIPTION"/>
		<Row TraitType="MINOR_CIV_FALAS_TRAIT" Name="LOC_MINOR_CIV_FALAS_TRAIT_NAME" Description="LOC_MINOR_CIV_FALAS_TRAIT_DESCRIPTION"/>
		<Row TraitType="MINOR_CIV_EOL_TRAIT" Name="LOC_MINOR_CIV_EOL_TRAIT_NAME" Description="LOC_MINOR_CIV_EOL_TRAIT_DESCRIPTION"/>
		<Row TraitType="MINOR_CIV_PETTYDWARVES_TRAIT" Name="LOC_MINOR_CIV_PETTYDWARVES_TRAIT_NAME" Description="LOC_MINOR_CIV_PETTYDWARVES_TRAIT_DESCRIPTION"/>
		<Row TraitType="MINOR_CIV_BALAR_TRAIT" Name="LOC_MINOR_CIV_BALAR_TRAIT_NAME" Description="LOC_MINOR_CIV_BALAR_TRAIT_DESCRIPTION"/>
		<Row TraitType="MINOR_CIV_SIRION_TRAIT" Name="LOC_MINOR_CIV_SIRION_TRAIT_NAME" Description="LOC_MINOR_CIV_SIRION_TRAIT_DESCRIPTION"/>
		<Row TraitType="MINOR_CIV_BRODDA_TRAIT" Name="LOC_MINOR_CIV_BRODDA_TRAIT_NAME" Description="LOC_MINOR_CIV_BRODDA_TRAIT_DESCRIPTION"/>
		<Row TraitType="MINOR_CIV_LORGAN_TRAIT" Name="LOC_MINOR_CIV_LORGAN_TRAIT_NAME" Description="LOC_MINOR_CIV_LORGAN_TRAIT_DESCRIPTION"/>
		<Row TraitType="MINOR_CIV_HADOR_TRAIT" Name="LOC_MINOR_CIV_HADOR_TRAIT_NAME" Description="LOC_MINOR_CIV_HADOR_TRAIT_DESCRIPTION"/>
		<Row TraitType="MINOR_CIV_BEOR_LADROS_TRAIT" Name="LOC_MINOR_CIV_BEOR_LADROS_TRAIT_NAME" Description="LOC_MINOR_CIV_BEOR_LADROS_TRAIT_DESCRIPTION"/>
		<Row TraitType="MINOR_CIV_DOR_CUARTHOL_TRAIT" Name="LOC_MINOR_CIV_DOR_CUARTHOL_TRAIT_NAME" Description="LOC_MINOR_CIV_DOR_CUARTHOL_TRAIT_DESCRIPTION"/>

	</Traits>

	<TraitModifiers>
		<Row TraitType="MINOR_CIV_BEOR_TRAIT" ModifierId="MINOR_CIV_BEOR_UNIQUE_INFLUENCE_TRADE_FAITH_BONUS"/>
		<Row TraitType="MINOR_CIV_HALADIN_TRAIT" ModifierId="MINOR_CIV_DRUADAN_UNIQUE_INFLUENCE_BONUS"/>
		<Row TraitType="MINOR_CIV_MARACH_TRAIT" ModifierId="MINOR_CIV_MARACH_UNIQUE_INFLUENCE_BONUS"/>
		<Row TraitType="MINOR_CIV_BOR_TRAIT" ModifierId="MINOR_CIV_BALCHOTH_UNIQUE_INFLUENCE_HORSE_BONUS"/>
		<Row TraitType="MINOR_CIV_BOR_TRAIT" ModifierId="MINOR_CIV_BALCHOTH_UNIQUE_INFLUENCE_SHEEP_BONUS"/>
		<Row TraitType="MINOR_CIV_ULFANG_TRAIT" ModifierId="MINOR_CIV_ULFANG_UNIQUE_INFLUENCE_BONUS"/>
		<Row TraitType="MINOR_CIV_BELEGOST_TRAIT" ModifierId="MINOR_CIV_DALE_UNIQUE_INFLUENCE_BONUS"/>
		<Row TraitType="MINOR_CIV_NOGROD_TRAIT" ModifierId="MINOR_CIV_IRONFISTS_UNIQUE_INFLUENCE_BONUS"/>
		<Row TraitType="MINOR_CIV_FALAS_TRAIT" ModifierId="MINOR_CIV_FALAS_UNIQUE_INFLUENCE_BONUS"/>
		<Row TraitType="MINOR_CIV_EOL_TRAIT" ModifierId="MINOR_CIV_EOL_UNIQUE_INFLUENCE_BONUS"/>
		<Row TraitType="MINOR_CIV_PETTYDWARVES_TRAIT" ModifierId="MINOR_CIV_PETTYDWARVES_UNIQUE_INFLUENCE_BONUS"/>
		<Row TraitType="MINOR_CIV_BALAR_TRAIT" ModifierId="MINOR_CIV_BALAR_UNIQUE_INFLUENCE_BONUS"/>
		<Row TraitType="MINOR_CIV_SIRION_TRAIT" ModifierId="MINOR_CIV_SIRION_UNIQUE_INFLUENCE_BONUS"/>
		<Row TraitType="MINOR_CIV_BRODDA_TRAIT" ModifierId="MINOR_CIV_BRODDA_UNIQUE_INFLUENCE_BONUS"/>
		<Row TraitType="MINOR_CIV_LORGAN_TRAIT" ModifierId="MINOR_CIV_IRONFISTS_UNIQUE_INFLUENCE_BONUS"/>
		<Row TraitType="MINOR_CIV_HADOR_TRAIT" ModifierId="MINOR_CIV_HADOR_UNIQUE_INFLUENCE_BONUS"/>
		<Row TraitType="MINOR_CIV_BEOR_LADROS_TRAIT" ModifierId="MINOR_CIV_BEOR_LADROS_UNIQUE_INFLUENCE_TRADE_CULTURE_BONUS"/>
		<Row TraitType="MINOR_CIV_BEOR_LADROS_TRAIT" ModifierId="MINOR_CIV_BEOR_LADROS_UNIQUE_INFLUENCE_TRADE_GOLD_BONUS"/>
		<Row TraitType="MINOR_CIV_DOR_CUARTHOL_TRAIT" ModifierId="MINOR_CIV_DOR_CUARTHOL_UNIQUE_INFLUENCE_BONUS"/>

	</TraitModifiers>

	<Modifiers>
		<Row>
			<ModifierId>MINOR_CIV_BEOR_UNIQUE_INFLUENCE_TRADE_FAITH_BONUS</ModifierId>
			<ModifierType>MODIFIER_ALL_PLAYERS_ATTACH_MODIFIER</ModifierType>
			<SubjectRequirementSetId>PLAYER_IS_SUZERAIN</SubjectRequirementSetId>
		</Row>
		<Row>
			<ModifierId>MINOR_CIV_BEOR_TRADE_FAITH_BONUS</ModifierId>
			<ModifierType>MODIFIER_PLAYER_CITIES_ADJUST_TRADE_ROUTE_YIELD_FROM_OTHERS</ModifierType>
		</Row>
		<Row>
			<ModifierId>MINOR_CIV_MARACH_UNIQUE_INFLUENCE_BONUS</ModifierId>
			<ModifierType>MODIFIER_ALL_PLAYERS_ATTACH_MODIFIER</ModifierType>
			<SubjectRequirementSetId>PLAYER_IS_SUZERAIN</SubjectRequirementSetId>
		</Row>
		<Row>
			<ModifierId>MARACH_DOMESTICWARWEARINESS</ModifierId>
			<ModifierType>MODIFIER_PLAYER_ADJUST_WAR_WEARINESS</ModifierType>
		</Row>
		<Row>
			<ModifierId>MINOR_CIV_ULFANG_UNIQUE_INFLUENCE_BONUS</ModifierId>
			<ModifierType>MODIFIER_ALL_PLAYERS_ATTACH_MODIFIER</ModifierType>
			<SubjectRequirementSetId>PLAYER_IS_SUZERAIN</SubjectRequirementSetId>
		</Row>
		<Row>
			<ModifierId>MINOR_CIV_ULFANG_ABILITY_BONUS</ModifierId>
			<ModifierType>MODIFIER_PLAYER_UNITS_GRANT_ABILITY</ModifierType>
		</Row>
		<Row>
			<ModifierId>MYLOTR_ULFANG_COMBAT</ModifierId>
			<ModifierType>MODIFIER_UNIT_ADJUST_COMBAT_STRENGTH</ModifierType>
		</Row>
		<Row>
			<ModifierId>MINOR_CIV_FALAS_UNIQUE_INFLUENCE_BONUS</ModifierId>
			<ModifierType>MODIFIER_ALL_PLAYERS_ATTACH_MODIFIER</ModifierType>
			<SubjectRequirementSetId>PLAYER_IS_SUZERAIN</SubjectRequirementSetId>
		</Row>
		<Row>
			<ModifierId>MINOR_CIV_FALAS_DISTRICTS_GOLD_BONUS</ModifierId>
			<ModifierType>MODIFIER_PLAYER_DISTRICTS_ADJUST_YIELD_CHANGE</ModifierType>
			<SubjectRequirementSetId>PLOT_IS_OR_ADJACENT_TO_COAST</SubjectRequirementSetId>
		</Row>
		<Row>
			<ModifierId>MINOR_CIV_EOL_UNIQUE_INFLUENCE_BONUS</ModifierId>
			<ModifierType>MODIFIER_ALL_PLAYERS_ATTACH_MODIFIER</ModifierType>
			<SubjectRequirementSetId>PLAYER_IS_SUZERAIN</SubjectRequirementSetId>
		</Row>
		<Row>
			<ModifierId>MYLOTR_EOL_PRODUCTION_ADJACENCY_FOREST</ModifierId>
			<ModifierType>MODIFIER_PLAYER_CITIES_FEATURE_ADJACENCY</ModifierType>
		</Row>
		<Row>
			<ModifierId>MINOR_CIV_PETTYDWARVES_UNIQUE_INFLUENCE_BONUS</ModifierId>
			<ModifierType>MODIFIER_ALL_PLAYERS_ATTACH_MODIFIER</ModifierType>
			<SubjectRequirementSetId>PLAYER_IS_SUZERAIN</SubjectRequirementSetId>
		</Row>
		<Row>
			<ModifierId>MYLOTR_PETTYDWARVES_MINES_CULTURE_MODIFIER</ModifierId>
			<ModifierType>MODIFIER_PLAYER_ADJUST_PLOT_YIELD</ModifierType>
			<SubjectRequirementSetId>PLOT_HAS_MINE_REQUIREMENTS</SubjectRequirementSetId>
		</Row>
		<Row>
			<ModifierId>MINOR_CIV_BALAR_UNIQUE_INFLUENCE_BONUS</ModifierId>
			<ModifierType>MODIFIER_ALL_PLAYERS_ATTACH_MODIFIER</ModifierType>
			<SubjectRequirementSetId>PLAYER_IS_SUZERAIN</SubjectRequirementSetId>
		</Row>
		<Row>
			<ModifierId>MINOR_CIV_BALAR_DISTRICTS_FAITH_BONUS</ModifierId>
			<ModifierType>MODIFIER_PLAYER_DISTRICTS_ADJUST_YIELD_CHANGE</ModifierType>
			<SubjectRequirementSetId>PLOT_IS_OR_ADJACENT_TO_COAST</SubjectRequirementSetId>
		</Row>
		<Row>
			<ModifierId>MINOR_CIV_SIRION_UNIQUE_INFLUENCE_BONUS</ModifierId>
			<ModifierType>MODIFIER_ALL_PLAYERS_ATTACH_MODIFIER</ModifierType>
			<SubjectRequirementSetId>PLAYER_IS_SUZERAIN</SubjectRequirementSetId>
		</Row>
		<Row>
			<ModifierId>MINOR_CIV_SIRION_DISTRICTS_CULTURE_BONUS</ModifierId>
			<ModifierType>MODIFIER_PLAYER_DISTRICTS_ADJUST_YIELD_CHANGE</ModifierType>
			<SubjectRequirementSetId>PLOT_IS_OR_ADJACENT_TO_COAST</SubjectRequirementSetId>
		</Row>
		<Row>
			<ModifierId>MINOR_CIV_BRODDA_UNIQUE_INFLUENCE_BONUS</ModifierId>
			<ModifierType>MODIFIER_ALL_PLAYERS_ATTACH_MODIFIER</ModifierType>
			<SubjectRequirementSetId>PLAYER_IS_SUZERAIN</SubjectRequirementSetId>
		</Row>
		<Row>
			<ModifierId>MINOR_CIV_BRODDA_FAITH_KILLS</ModifierId>
			<ModifierType>MODIFIER_PLAYER_UNITS_ADJUST_POST_COMBAT_YIELD</ModifierType>
		</Row>
		<Row>
			<ModifierId>MINOR_CIV_HADOR_UNIQUE_INFLUENCE_BONUS</ModifierId>
			<ModifierType>MODIFIER_ALL_PLAYERS_ATTACH_MODIFIER</ModifierType>
			<SubjectRequirementSetId>PLAYER_IS_SUZERAIN</SubjectRequirementSetId>
		</Row>
		<Row>
			<ModifierId>MINOR_CIV_HADOR_ABILITY_BONUS</ModifierId>
			<ModifierType>MODIFIER_PLAYER_UNITS_GRANT_ABILITY</ModifierType>
		</Row>
		<Row>
			<ModifierId>MINOR_CIV_BEOR_LADROS_UNIQUE_INFLUENCE_TRADE_CULTURE_BONUS</ModifierId>
			<ModifierType>MODIFIER_ALL_PLAYERS_ATTACH_MODIFIER</ModifierType>
			<SubjectRequirementSetId>PLAYER_IS_SUZERAIN</SubjectRequirementSetId>
		</Row>
		<Row>
			<ModifierId>MINOR_CIV_BEOR_LADROS_CULTURE_TRADE_ROUTE_YIELD_BONUS</ModifierId>
			<ModifierType>MODIFIER_PLAYER_CITIES_ADJUST_CITY_STATE_TRADE_ROUTE_DISTRICT_YIELD</ModifierType>
		</Row>
		<Row>
			<ModifierId>MINOR_CIV_BEOR_LADROS_UNIQUE_INFLUENCE_TRADE_GOLD_BONUS</ModifierId>
			<ModifierType>MODIFIER_ALL_PLAYERS_ATTACH_MODIFIER</ModifierType>
			<SubjectRequirementSetId>PLAYER_IS_SUZERAIN</SubjectRequirementSetId>
		</Row>
		<Row>
			<ModifierId>MINOR_CIV_BEOR_LADROS_GOLD_TRADE_ROUTE_YIELD_BONUS</ModifierId>
			<ModifierType>MODIFIER_PLAYER_CITIES_ADJUST_CITY_STATE_TRADE_ROUTE_DISTRICT_YIELD</ModifierType>
		</Row>
		<Row>
			<ModifierId>MINOR_CIV_DOR_CUARTHOL_UNIQUE_INFLUENCE_BONUS</ModifierId>
			<ModifierType>MODIFIER_ALL_PLAYERS_ATTACH_MODIFIER</ModifierType>
			<SubjectRequirementSetId>PLAYER_IS_SUZERAIN</SubjectRequirementSetId>
		</Row>
		<Row>
			<ModifierId>MINOR_CIV_DOR_CUARTHOL_GOLD_KILLS</ModifierId>
			<ModifierType>MODIFIER_PLAYER_UNITS_ADJUST_POST_COMBAT_YIELD</ModifierType>
		</Row>
	</Modifiers>

	<ModifierArguments>
		<Row>
			<ModifierId>MINOR_CIV_BEOR_UNIQUE_INFLUENCE_TRADE_FAITH_BONUS</ModifierId>
			<Name>ModifierId</Name>
			<Value>MINOR_CIV_BEOR_TRADE_FAITH_BONUS</Value>
		</Row>
		<Row>
			<ModifierId>MINOR_CIV_BEOR_TRADE_FAITH_BONUS</ModifierId>
			<Name>YieldType</Name>
			<Value>YIELD_FAITH</Value>
		</Row>
		<Row>
			<ModifierId>MINOR_CIV_BEOR_TRADE_FAITH_BONUS</ModifierId>
			<Name>Amount</Name>
			<Value>2</Value>
		</Row>
		<Row>
			<ModifierId>MINOR_CIV_MARACH_UNIQUE_INFLUENCE_BONUS</ModifierId>
			<Name>ModifierId</Name>
			<Value>MARACH_DOMESTICWARWEARINESS</Value>
		</Row>
		<Row>
			<ModifierId>MARACH_DOMESTICWARWEARINESS</ModifierId>
			<Name>Amount</Name>
			<Value>-50</Value>
		</Row>
		<Row>
			<ModifierId>MARACH_DOMESTICWARWEARINESS</ModifierId>
			<Name>Domestic</Name>
			<Value>true</Value>
		</Row>
		<Row>
			<ModifierId>MINOR_CIV_ULFANG_UNIQUE_INFLUENCE_BONUS</ModifierId>
			<Name>ModifierId</Name>
			<Value>MINOR_CIV_ULFANG_ABILITY_BONUS</Value>
		</Row>
		<Row>
			<ModifierId>MINOR_CIV_ULFANG_ABILITY_BONUS</ModifierId>
			<Name>AbilityType</Name>
			<Value>ABILITY_ULFANG_GRANT</Value>
		</Row>
		<Row>
			<ModifierId>MYLOTR_ULFANG_COMBAT</ModifierId>
			<Name>Amount</Name>
			<Value>4</Value>
		</Row>
		<Row>
			<ModifierId>MINOR_CIV_FALAS_UNIQUE_INFLUENCE_BONUS</ModifierId>
			<Name>ModifierId</Name>
			<Value>MINOR_CIV_FALAS_DISTRICTS_GOLD_BONUS</Value>
		</Row>
		<Row>
			<ModifierId>MINOR_CIV_FALAS_DISTRICTS_GOLD_BONUS</ModifierId>
			<Name>Amount</Name>
			<Value>1</Value>
		</Row>
		<Row>
			<ModifierId>MINOR_CIV_FALAS_DISTRICTS_GOLD_BONUS</ModifierId>
			<Name>YieldType</Name>
			<Value>YIELD_GOLD</Value>
		</Row>
		<Row>
			<ModifierId>MINOR_CIV_EOL_UNIQUE_INFLUENCE_BONUS</ModifierId>
			<Name>ModifierId</Name>
			<Value>MYLOTR_EOL_PRODUCTION_ADJACENCY_FOREST</Value>
		</Row>
		<Row>
			<ModifierId>MYLOTR_EOL_PRODUCTION_ADJACENCY_FOREST</ModifierId>
			<Name>DistrictType</Name>
			<Value>DISTRICT_INDUSTRIAL_ZONE</Value>
		</Row>
		<Row>
			<ModifierId>MYLOTR_EOL_PRODUCTION_ADJACENCY_FOREST</ModifierId>
			<Name>FeatureType</Name>
			<Value>FEATURE_FOREST</Value>
		</Row>
		<Row>
			<ModifierId>MYLOTR_EOL_PRODUCTION_ADJACENCY_FOREST</ModifierId>
			<Name>YieldType</Name>
			<Value>YIELD_PRODUCTION</Value>
		</Row>
		<Row>
			<ModifierId>MYLOTR_EOL_PRODUCTION_ADJACENCY_FOREST</ModifierId>
			<Name>Amount</Name>
			<Value>1</Value>
		</Row>
		<Row>
			<ModifierId>MYLOTR_EOL_PRODUCTION_ADJACENCY_FOREST</ModifierId>
			<Name>Description</Name>
			<Value>LOC_MYLOTR_DISTRICT_FOREST_PRODUCTION</Value>
		</Row>
		<Row>
			<ModifierId>MINOR_CIV_PETTYDWARVES_UNIQUE_INFLUENCE_BONUS</ModifierId>
			<Name>ModifierId</Name>
			<Value>MYLOTR_PETTYDWARVES_MINES_CULTURE_MODIFIER</Value>
		</Row>
		<Row>
			<ModifierId>MYLOTR_PETTYDWARVES_MINES_CULTURE_MODIFIER</ModifierId>
			<Name>YieldType</Name>
			<Value>YIELD_CULTURE</Value>
		</Row>
		<Row>
			<ModifierId>MYLOTR_PETTYDWARVES_MINES_CULTURE_MODIFIER</ModifierId>
			<Name>Amount</Name>
			<Value>1</Value>
		</Row>
		<Row>
			<ModifierId>MINOR_CIV_BALAR_UNIQUE_INFLUENCE_BONUS</ModifierId>
			<Name>ModifierId</Name>
			<Value>MINOR_CIV_BALAR_DISTRICTS_FAITH_BONUS</Value>
		</Row>
		<Row>
			<ModifierId>MINOR_CIV_BALAR_DISTRICTS_FAITH_BONUS</ModifierId>
			<Name>Amount</Name>
			<Value>1</Value>
		</Row>
		<Row>
			<ModifierId>MINOR_CIV_BALAR_DISTRICTS_FAITH_BONUS</ModifierId>
			<Name>YieldType</Name>
			<Value>YIELD_FAITH</Value>
		</Row>
		<Row>
			<ModifierId>MINOR_CIV_SIRION_UNIQUE_INFLUENCE_BONUS</ModifierId>
			<Name>ModifierId</Name>
			<Value>MINOR_CIV_SIRION_DISTRICTS_CULTURE_BONUS</Value>
		</Row>
		<Row>
			<ModifierId>MINOR_CIV_SIRION_DISTRICTS_CULTURE_BONUS</ModifierId>
			<Name>Amount</Name>
			<Value>1</Value>
		</Row>
		<Row>
			<ModifierId>MINOR_CIV_SIRION_DISTRICTS_CULTURE_BONUS</ModifierId>
			<Name>YieldType</Name>
			<Value>YIELD_RELIGIOUS</Value>
		</Row>
		<Row>
			<ModifierId>MINOR_CIV_BRODDA_UNIQUE_INFLUENCE_BONUS</ModifierId>
			<Name>ModifierId</Name>
			<Value>MINOR_CIV_BRODDA_FAITH_KILLS</Value>
		</Row>
		<Row>
			<ModifierId>MINOR_CIV_BRODDA_FAITH_KILLS</ModifierId>
			<Name>YieldType</Name>
			<Value>YIELD_FAITH</Value>
		</Row>
		<Row>
			<ModifierId>MINOR_CIV_BRODDA_FAITH_KILLS</ModifierId>
			<Name>PercentDefeatedStrength</Name>
			<Value>20</Value>
		</Row>
		<Row>
			<ModifierId>MINOR_CIV_HADOR_UNIQUE_INFLUENCE_BONUS</ModifierId>
			<Name>ModifierId</Name>
			<Value>MINOR_CIV_HADOR_ABILITY_BONUS</Value>
		</Row>
		<Row>
			<ModifierId>MINOR_CIV_HADOR_ABILITY_BONUS</ModifierId>
			<Name>AbilityType</Name>
			<Value>ABILITY_MYLOTR_MELEE_HILLS_BONUS</Value>
		</Row>
		<Row>
			<ModifierId>MINOR_CIV_BEOR_LADROS_UNIQUE_INFLUENCE_TRADE_CULTURE_BONUS</ModifierId>
			<Name>ModifierId</Name>
			<Value>MINOR_CIV_BEOR_LADROS_CULTURE_TRADE_ROUTE_YIELD_BONUS</Value>
		</Row>
		<Row>
			<ModifierId>MINOR_CIV_BEOR_LADROS_CULTURE_TRADE_ROUTE_YIELD_BONUS</ModifierId>
			<Name>YieldType</Name>
			<Value>YIELD_CULTURE</Value>
		</Row>
		<Row>
			<ModifierId>MINOR_CIV_BEOR_LADROS_CULTURE_TRADE_ROUTE_YIELD_BONUS</ModifierId>
			<Name>Amount</Name>
			<Value>2</Value>
		</Row>
		<Row>
			<ModifierId>MINOR_CIV_BEOR_LADROS_UNIQUE_INFLUENCE_TRADE_GOLD_BONUS</ModifierId>
			<Name>ModifierId</Name>
			<Value>MINOR_CIV_BEOR_LADROS_GOLD_TRADE_ROUTE_YIELD_BONUS</Value>
		</Row>
		<Row>
			<ModifierId>MINOR_CIV_BEOR_LADROS_GOLD_TRADE_ROUTE_YIELD_BONUS</ModifierId>
			<Name>YieldType</Name>
			<Value>YIELD_GOLD</Value>
		</Row>
		<Row>
			<ModifierId>MINOR_CIV_BEOR_LADROS_GOLD_TRADE_ROUTE_YIELD_BONUS</ModifierId>
			<Name>Amount</Name>
			<Value>1</Value>
		</Row>
		<Row>
			<ModifierId>MINOR_CIV_DOR_CUARTHOL_UNIQUE_INFLUENCE_BONUS</ModifierId>
			<Name>ModifierId</Name>
			<Value>MINOR_CIV_DOR_CUARTHOL_GOLD_KILLS</Value>
		</Row>
		<Row>
			<ModifierId>MINOR_CIV_DOR_CUARTHOL_GOLD_KILLS</ModifierId>
			<Name>YieldType</Name>
			<Value>YIELD_GOLD</Value>
		</Row>
		<Row>
			<ModifierId>MINOR_CIV_DOR_CUARTHOL_GOLD_KILLS</ModifierId>
			<Name>PercentDefeatedStrength</Name>
			<Value>25</Value>
		</Row>
	</ModifierArguments>

	<ModifierStrings>
		<Row ModifierId="MYLOTR_ULFANG_COMBAT" Context="Preview" Text="LOC_MINOR_CIV_ULFANG_TRAIT_DESCRIPTION"/>
	</ModifierStrings>
	<TypeTags>
		<Row Type="ABILITY_ULFANG_GRANT" Tag="CLASS_LIGHT_CAVALRY"/>
	</TypeTags>
	<UnitAbilities>
		<Row UnitAbilityType="ABILITY_ULFANG_GRANT" Name="LOC_ABILITY_ULFANG_GRANT_NAME" Description="LOC_ABILITY_ULFANG_GRANT_DESCRIPTION" Inactive="true"/>
	</UnitAbilities>
	<UnitAbilityModifiers>
		<Row>
			<UnitAbilityType>ABILITY_ULFANG_GRANT</UnitAbilityType>
			<ModifierId>MYLOTR_ULFANG_COMBAT</ModifierId>
		</Row>
	</UnitAbilityModifiers>
	
	<TypeProperties>
		<Row Type="CIVILIZATION_BEOR" Name="CityStateCategory" Value="CULTURAL"/>
		<Row Type="CIVILIZATION_HALADIN" Name="CityStateCategory" Value="RELIGIOUS"/>
		<Row Type="CIVILIZATION_MARACH" Name="CityStateCategory" Value="MILITARISTIC"/>
		<Row Type="CIVILIZATION_BOR" Name="CityStateCategory" Value="MILITARISTIC"/>
		<Row Type="CIVILIZATION_ULFANG" Name="CityStateCategory" Value="MILITARISTIC"/>
		<Row Type="CIVILIZATION_BELEGOST" Name="CityStateCategory" Value="TRADE"/>
		<Row Type="CIVILIZATION_NOGROD" Name="CityStateCategory" Value="INDUSTRIAL"/>
		<Row Type="CIVILIZATION_FALAS" Name="CityStateCategory" Value="TRADE"/>
		<Row Type="CIVILIZATION_EOL" Name="CityStateCategory" Value="INDUSTRIAL"/>
		<Row Type="CIVILIZATION_PETTYDWARVES" Name="CityStateCategory" Value="CULTURAL"/>
		<Row Type="CIVILIZATION_BALAR" Name="CityStateCategory" Value="RELIGIOUS"/>
		<Row Type="CIVILIZATION_SIRION" Name="CityStateCategory" Value="CULTURAL"/>
		<Row Type="CIVILIZATION_BRODDA" Name="CityStateCategory" Value="RELIGIOUS"/>
		<Row Type="CIVILIZATION_LORGAN" Name="CityStateCategory" Value="INDUSTRIAL"/>
		<Row Type="CIVILIZATION_HADOR" Name="CityStateCategory" Value="MILITARISTIC"/>
		<Row Type="CIVILIZATION_BEOR_LADROS" Name="CityStateCategory" Value="CULTURAL"/>
		<Row Type="CIVILIZATION_DOR_CUARTHOL" Name="CityStateCategory" Value="MILITARISTIC"/>

	</TypeProperties>

	<Civilizations>
		<Row CivilizationType="CIVILIZATION_BEOR" Name="LOC_BEOR_NAME" Description="LOC_BEOR_DESCRIPTION" Adjective="LOC_BEOR_ADJECTIVE" StartingCivilizationLevelType="CIVILIZATION_LEVEL_CITY_STATE" RandomCityNameDepth="1"/>
		<Row CivilizationType="CIVILIZATION_HALADIN" Name="LOC_HALADIN_NAME" Description="LOC_HALADIN_DESCRIPTION" Adjective="LOC_HALADIN_ADJECTIVE" StartingCivilizationLevelType="CIVILIZATION_LEVEL_CITY_STATE" RandomCityNameDepth="1"/>
		<Row CivilizationType="CIVILIZATION_MARACH" Name="LOC_MARACH_NAME" Description="LOC_MARACH_DESCRIPTION" Adjective="LOC_MARACH_ADJECTIVE" StartingCivilizationLevelType="CIVILIZATION_LEVEL_CITY_STATE" RandomCityNameDepth="1"/>
		<Row CivilizationType="CIVILIZATION_BOR" Name="LOC_BOR_NAME" Description="LOC_BOR_DESCRIPTION" Adjective="LOC_BOR_ADJECTIVE" StartingCivilizationLevelType="CIVILIZATION_LEVEL_CITY_STATE" RandomCityNameDepth="1"/>
		<Row CivilizationType="CIVILIZATION_ULFANG" Name="LOC_ULFANG_NAME" Description="LOC_ULFANG_DESCRIPTION" Adjective="LOC_ULFANG_ADJECTIVE" StartingCivilizationLevelType="CIVILIZATION_LEVEL_CITY_STATE" RandomCityNameDepth="1"/>
		<Row CivilizationType="CIVILIZATION_BELEGOST" Name="LOC_BELEGOST_NAME" Description="LOC_BELEGOST_DESCRIPTION" Adjective="LOC_BELEGOST_ADJECTIVE" StartingCivilizationLevelType="CIVILIZATION_LEVEL_CITY_STATE" RandomCityNameDepth="1"/>
		<Row CivilizationType="CIVILIZATION_NOGROD" Name="LOC_NOGROD_NAME" Description="LOC_NOGROD_DESCRIPTION" Adjective="LOC_NOGROD_ADJECTIVE" StartingCivilizationLevelType="CIVILIZATION_LEVEL_CITY_STATE" RandomCityNameDepth="1"/>
		<Row CivilizationType="CIVILIZATION_FALAS" Name="LOC_FALAS_NAME" Description="LOC_FALAS_DESCRIPTION" Adjective="LOC_FALAS_ADJECTIVE" StartingCivilizationLevelType="CIVILIZATION_LEVEL_CITY_STATE" RandomCityNameDepth="1"/>
		<Row CivilizationType="CIVILIZATION_EOL" Name="LOC_EOL_NAME" Description="LOC_EOL_DESCRIPTION" Adjective="LOC_EOL_ADJECTIVE" StartingCivilizationLevelType="CIVILIZATION_LEVEL_CITY_STATE" RandomCityNameDepth="1"/>
		<Row CivilizationType="CIVILIZATION_PETTYDWARVES" Name="LOC_PETTYDWARVES_NAME" Description="LOC_PETTYDWARVES_DESCRIPTION" Adjective="LOC_PETTYDWARVES_ADJECTIVE" StartingCivilizationLevelType="CIVILIZATION_LEVEL_CITY_STATE" RandomCityNameDepth="1"/>
		<Row CivilizationType="CIVILIZATION_BALAR" Name="LOC_BALAR_NAME" Description="LOC_BALAR_DESCRIPTION" Adjective="LOC_BALAR_ADJECTIVE" StartingCivilizationLevelType="CIVILIZATION_LEVEL_CITY_STATE" RandomCityNameDepth="1"/>
		<Row CivilizationType="CIVILIZATION_SIRION" Name="LOC_SIRION_NAME" Description="LOC_SIRION_DESCRIPTION" Adjective="LOC_SIRION_ADJECTIVE" StartingCivilizationLevelType="CIVILIZATION_LEVEL_CITY_STATE" RandomCityNameDepth="1"/>
		<Row CivilizationType="CIVILIZATION_BRODDA" Name="LOC_BRODDA_NAME" Description="LOC_BRODDA_DESCRIPTION" Adjective="LOC_BRODDA_ADJECTIVE" StartingCivilizationLevelType="CIVILIZATION_LEVEL_CITY_STATE" RandomCityNameDepth="1"/>
		<Row CivilizationType="CIVILIZATION_LORGAN" Name="LOC_LORGAN_NAME" Description="LOC_LORGAN_DESCRIPTION" Adjective="LOC_LORGAN_ADJECTIVE" StartingCivilizationLevelType="CIVILIZATION_LEVEL_CITY_STATE" RandomCityNameDepth="1"/>
		<Row CivilizationType="CIVILIZATION_HADOR" Name="LOC_HADOR_NAME" Description="LOC_HADOR_DESCRIPTION" Adjective="LOC_HADOR_ADJECTIVE" StartingCivilizationLevelType="CIVILIZATION_LEVEL_CITY_STATE" RandomCityNameDepth="1"/>
		<Row CivilizationType="CIVILIZATION_BEOR_LADROS" Name="LOC_BEOR_LADROS_NAME" Description="LOC_BEOR_LADROS_DESCRIPTION" Adjective="LOC_BEOR_LADROS_ADJECTIVE" StartingCivilizationLevelType="CIVILIZATION_LEVEL_CITY_STATE" RandomCityNameDepth="1"/>
		<Row CivilizationType="CIVILIZATION_DOR_CUARTHOL" Name="LOC_DOR_CUARTHOL_NAME" Description="LOC_DOR_CUARTHOL_DESCRIPTION" Adjective="LOC_DOR_CUARTHOL_ADJECTIVE" StartingCivilizationLevelType="CIVILIZATION_LEVEL_CITY_STATE" RandomCityNameDepth="1"/>

	</Civilizations>

	<CivilizationLeaders>
		<Row CivilizationType="CIVILIZATION_BEOR" LeaderType="LEADER_MINOR_CIV_BEOR" CapitalName="LOC_CITY_NAME_BEOR"/>
		<Row CivilizationType="CIVILIZATION_HALADIN" LeaderType="LEADER_MINOR_CIV_HALADIN" CapitalName="LOC_CITY_NAME_HALADIN"/>
		<Row CivilizationType="CIVILIZATION_MARACH" LeaderType="LEADER_MINOR_CIV_MARACH" CapitalName="LOC_CITY_NAME_MARACH"/>
		<Row CivilizationType="CIVILIZATION_BOR" LeaderType="LEADER_MINOR_CIV_BOR" CapitalName="LOC_CITY_NAME_BOR"/>
		<Row CivilizationType="CIVILIZATION_ULFANG" LeaderType="LEADER_MINOR_CIV_ULFANG" CapitalName="LOC_CITY_NAME_ULFANG"/>
		<Row CivilizationType="CIVILIZATION_BELEGOST" LeaderType="LEADER_MINOR_CIV_BELEGOST" CapitalName="LOC_CITY_NAME_BELEGOST"/>
		<Row CivilizationType="CIVILIZATION_NOGROD" LeaderType="LEADER_MINOR_CIV_NOGROD" CapitalName="LOC_CITY_NAME_NOGROD"/>
		<Row CivilizationType="CIVILIZATION_FALAS" LeaderType="LEADER_MINOR_CIV_FALAS" CapitalName="LOC_CITY_NAME_FALAS"/>
		<Row CivilizationType="CIVILIZATION_EOL" LeaderType="LEADER_MINOR_CIV_EOL" CapitalName="LOC_CITY_NAME_EOL"/>
		<Row CivilizationType="CIVILIZATION_PETTYDWARVES" LeaderType="LEADER_MINOR_CIV_PETTYDWARVES" CapitalName="LOC_CITY_NAME_BARENNIBINNOEG"/>
		<Row CivilizationType="CIVILIZATION_BALAR" LeaderType="LEADER_MINOR_CIV_BALAR" CapitalName="LOC_CITY_NAME_BALAR"/>
		<Row CivilizationType="CIVILIZATION_SIRION" LeaderType="LEADER_MINOR_CIV_SIRION" CapitalName="LOC_CITY_NAME_HAVENS_OF_SIRION"/>
		<Row CivilizationType="CIVILIZATION_BRODDA" LeaderType="LEADER_MINOR_CIV_BRODDA" CapitalName="LOC_CITY_NAME_BRODDA"/>
		<Row CivilizationType="CIVILIZATION_LORGAN" LeaderType="LEADER_MINOR_CIV_LORGAN" CapitalName="LOC_CITY_NAME_LORGAN"/>
		<Row CivilizationType="CIVILIZATION_HADOR" LeaderType="LEADER_MINOR_CIV_HADOR" CapitalName="LOC_CITY_NAME_HADOR"/>
		<Row CivilizationType="CIVILIZATION_BEOR_LADROS" LeaderType="LEADER_MINOR_CIV_BEOR_LADROS" CapitalName="LOC_CITY_NAME_BEOR_LADROS"/>
		<Row CivilizationType="CIVILIZATION_DOR_CUARTHOL" LeaderType="LEADER_MINOR_CIV_DOR_CUARTHOL" CapitalName="LOC_CITY_NAME_DOR_CUARTHOL"/>

	</CivilizationLeaders>

	<CityNames>
		<Row CivilizationType="CIVILIZATION_BEOR" CityName="LOC_CITY_NAME_BEOR"/>
		<Row CivilizationType="CIVILIZATION_HALADIN" CityName="LOC_CITY_NAME_HALADIN"/>
		<Row CivilizationType="CIVILIZATION_MARACH" CityName="LOC_CITY_NAME_MARACH"/>
		<Row CivilizationType="CIVILIZATION_BOR" CityName="LOC_CITY_NAME_BOR"/>
		<Row CivilizationType="CIVILIZATION_ULFANG" CityName="LOC_CITY_NAME_ULFANG"/>
		<Row CivilizationType="CIVILIZATION_BELEGOST" CityName="LOC_CITY_NAME_BELEGOST"/>
		<Row CivilizationType="CIVILIZATION_NOGROD" CityName="LOC_CITY_NAME_NOGROD"/>
		<Row CivilizationType="CIVILIZATION_FALAS" CityName="LOC_CITY_NAME_FALAS"/>
		<Row CivilizationType="CIVILIZATION_EOL" CityName="LOC_CITY_NAME_EOL"/>
		<Row CivilizationType="CIVILIZATION_PETTYDWARVES" CityName="LOC_CITY_NAME_BARENNIBINNOEG"/>
		<Row CivilizationType="CIVILIZATION_PETTYDWARVES" CityName="LOC_CITY_NAME_NULUKKIZDIN"/>
		<Row CivilizationType="CIVILIZATION_BALAR" CityName="LOC_CITY_NAME_BALAR"/>
		<Row CivilizationType="CIVILIZATION_SIRION" CityName="LOC_CITY_NAME_HAVENS_OF_SIRION"/>
		<Row CivilizationType="CIVILIZATION_BRODDA" CityName="LOC_CITY_NAME_BRODDA"/>
		<Row CivilizationType="CIVILIZATION_LORGAN" CityName="LOC_CITY_NAME_LORGAN"/>
		<Row CivilizationType="CIVILIZATION_HADOR" CityName="LOC_CITY_NAME_HADOR"/>
		<Row CivilizationType="CIVILIZATION_BEOR_LADROS" CityName="LOC_CITY_NAME_BEOR_LADROS"/>
		<Row CivilizationType="CIVILIZATION_DOR_CUARTHOL" CityName="LOC_CITY_NAME_DOR_CUARTHOL"/>

	</CityNames>
</GameData>
